.gitignore
LICENCE
MANIFEST.in
Makefile
README.md
grid.jpg
out.txt
pyproject.toml
setup.cfg
seed_shuffler.egg-info/PKG-INFO
seed_shuffler.egg-info/SOURCES.txt
seed_shuffler.egg-info/dependency_links.txt
seed_shuffler.egg-info/entry_points.txt
seed_shuffler.egg-info/not-zip-safe
seed_shuffler.egg-info/requires.txt
seed_shuffler.egg-info/top_level.txt
shuffler/__init__.py
shuffler/_version.py
shuffler/main.py
shuffler/uheprng.py
shuffler/wordlists/__init__.py
shuffler/wordlists/english.txt