Metadata-Version: 2.1
Name: seed-shuffler
Version: 0.0.0
Summary: BIP39 Seed Shuffler
Home-page: https://github.com/amarjen/seed-shuffler
Author: Tony M. Jenkins
Author-email: tonymj@proton.me
License: MIT Licence
Keywords: bitcoin,bip39,uheprng
Classifier: Programming Language :: Python :: 3
Classifier: Environment :: Console
Classifier: Development Status :: 3 - Alpha
Classifier: License :: OSI Approved :: MIT License
License-File: LICENCE
